xboinc/__init__.py
xboinc/df_wu.py
xboinc/executable/CMakeLists.txt
xboinc/executable/__init__.py
xboinc/executable/generate.py
xboinc/executable/main.cpp
xboinc/executable/version.h
xboinc/executable/xtrack.c
xboinc/executable/xtrack.h
xboinc/general.py
xboinc/register.py
xboinc/retrieve.py
xboinc/server/__init__.py
xboinc/server/paths.py
xboinc/server/tools.py
xboinc/simulation_io/__init__.py
xboinc/simulation_io/default_tracker.py
xboinc/simulation_io/input.py
xboinc/simulation_io/output.py
xboinc/simulation_io/version.py
xboinc/submit.py
xboinc/user.py
xboinc-0.6.0.dist-info/METADATA
xboinc-0.6.0.dist-info/WHEEL
xboinc-0.6.0.dist-info/licenses/LICENSE
xboinc-0.6.0.dist-info/licenses/NOTICE
xboinc-0.6.0.dist-info/RECORD
