Metadata-Version: 2.4
Name: xboinc
Version: 0.6.0
Summary: Xsuite BOINC interface
License: Apache 2.0
License-File: LICENSE
License-File: NOTICE
Author: Frederik F. Van der Veken
Author-email: frederik@cern.ch
Requires-Python: >=3.9
Classifier: License :: Other/Proprietary License
Classifier: Programming Language :: Python :: 3
Classifier: Programming Language :: Python :: 3.9
Classifier: Programming Language :: Python :: 3.10
Classifier: Programming Language :: Python :: 3.11
Classifier: Programming Language :: Python :: 3.12
Classifier: Programming Language :: Python :: 3.13
Classifier: Programming Language :: Python :: 3.14
Requires-Dist: numpy (>=1.0)
Requires-Dist: packaging (>=23.0)
Requires-Dist: xaux (>=0.3.11)
Requires-Dist: xcoll (==0.9.1)
Requires-Dist: xdeps (==0.10.10)
Requires-Dist: xfields (==0.25.8)
Requires-Dist: xobjects (==0.5.12)
Requires-Dist: xpart (==0.23.7)
Requires-Dist: xsuite (==0.45.15)
Requires-Dist: xtrack (==0.98.12)
Project-URL: Homepage, https://github.com/xsuite/xboinc
Project-URL: Repository, https://github.com/xsuite/xboinc
